pycord/i18n/__init__.py
pycord_i18n-1.2.1.dist-info/LICENSE.txt
pycord_i18n-1.2.1.dist-info/METADATA
pycord_i18n-1.2.1.dist-info/WHEEL
pycord_i18n-1.2.1.dist-info/top_level.txt
pycord_i18n-1.2.1.dist-info/RECORD
