Metadata-Version: 2.1
Name: pycord-i18n
Version: 1.2.1
Summary: Internationalization for Pycord
Home-page: https://github.com/Dorukyum/pycord-i18n
Author: Dorukyum
License: MIT
Project-URL: Source, https://github.com/Dorukyum/pycord-i18n
Keywords: Pycord
Classifier: License :: OSI Approved :: MIT License
Classifier: Programming Language :: Python :: 3
License-File: LICENSE.txt
Requires-Dist: py-cord >=2.0.0
